qt_unraveling/__init__.py
qt_unraveling/current_measurement.py
qt_unraveling/diffusive_trajectory.py
qt_unraveling/feedback_trajectory.py
qt_unraveling/integrators.py
qt_unraveling/jumpy_trajectory.py
qt_unraveling/misc_func.py
qt_unraveling/qt_unraveling.py
qt_unraveling/usual_operators.py
qt_unraveling-0.2.8.2.dist-info/METADATA
qt_unraveling-0.2.8.2.dist-info/WHEEL
qt_unraveling-0.2.8.2.dist-info/top_level.txt
qt_unraveling-0.2.8.2.dist-info/RECORD
