Metadata-Version: 2.1
Name: qt-unraveling
Version: 0.2.8.2
Summary: Library focused on simulate quantum trajectories with different unravelings
Home-page: https://github.com/dvelozad/qt-unraveling-python
Download-URL: https://github.com/dvelozad/qt-unraveling-python/archive/refs/tags/v0.2.7.tar.gz
Author: Diego Veloza Diaz
Author-email: dvelozad@unal.edu.co
Keywords: python,quantum control,unraveling,master equation,lindblad,open systems
Classifier: Development Status :: 3 - Alpha
Classifier: Intended Audience :: Science/Research
Classifier: Topic :: Scientific/Engineering :: Physics
Classifier: License :: OSI Approved :: MIT License
Classifier: Programming Language :: Python :: 3
Classifier: Programming Language :: Python :: 3.4
Classifier: Programming Language :: Python :: 3.5
Classifier: Programming Language :: Python :: 3.6
Classifier: Programming Language :: Python :: 3.9
Classifier: Programming Language :: Python :: 3.10
Requires-Dist: numpy
Requires-Dist: numba
Requires-Dist: scipy
Requires-Dist: matplotlib
Requires-Dist: multiprocess
